Workbook

Sheet Prospectos
A1: Nº | B1: Nombre / Organización | C1: Segmento | D1: País | E1: Ciudad / Dirección | F1: Plataforma y alcance | G1: Contacto verificado | H1: Motivación (encaje con ViveMucho.com / VivaMucho.com) | I1: Ajuste temático (1-5) | J1: Alcance (1-5) | K1: Contacto disp. (0-2) | L1: Puntuación | M1: Prioridad | N1: Fuente
A2: 1 | B2: Dr. Ángel Durántez – Clínica Neleva | C2: Clínica de longevidad / médico pionero | D2: España | E2: Madrid (C/Claudio Coello 19, 1ª planta, 28001) | F2: Pionero de Age Management en España (+30 años); autor de "Joven a los 100"; Forbes 100 mejores médicos | G2: atencionpaciente@clinicaneleva.com; info@drdurantez.es; Tel +34 915 622 278; +34 699 595 619 | H2: Su marca personal ES "vivir más y mejor": el dominio es su mensaje literal; ideal como portal de sus programas y libros | I2: 5 | J2: 5 | K2: 2 | L2: =I2+J2+K2 -> 12 | M2: =IF(L2>=10,"Alta",IF(L2>=7,"Media","Baja")) -> Alta | N2: Fuente
A3: 2 | B3: Age Reversal – Dr. Hernández Poveda | C3: Clínica de longevidad premium | D3: España | E3: Madrid-Pozuelo de Alarcón, Barcelona y Mallorca | F3: Chequeos con +1.000 biomarcadores; membresías de 10.000€ a 35.000€ | G3: info@agereversal.es; +34 650 344 806; formulario agereversal.es/join | H3: Clínica en expansión (3 sedes) con clientela premium; un dominio emocional en español refuerza su captación de alto valor | I3: 5 | J3: 4 | K3: 2 | L3: =I3+J3+K3 -> 11 | M3: =IF(L3>=10,"Alta",IF(L3>=7,"Media","Baja")) -> Alta | N3: Fuente
A4: 3 | B4: SHA Wellness Clinic – Dr. Vicente Mera | C4: Clínica wellness de lujo | D4: España | E4: Alfaz del Pi, Alicante (también México y Emiratos) | F4: Referencia mundial del wellness; Mera premiado como mejor médico europeo en antienvejecimiento | G4: sales@shawellness.com; +34 865 614 147 | H4: Marca global de "vivir más y mejor"; el dominio serviría para campañas en español y comunidad de pacientes | I4: 4 | J4: 5 | K4: 2 | L4: =I4+J4+K4 -> 11 | M4: =IF(L4>=10,"Alta",IF(L4>=7,"Media","Baja")) -> Alta | N4: Fuente
A5: 4 | B5: Buchinger Wilhelmi Marbella | C5: Clínica de ayuno terapéutico / wellness | D5: España | E5: Marbella, Málaga (Av. Buchinger 15) | F5: Clínica líder mundial en ayuno; organiza Congreso de Longevidad anual en Marbella (150+ expertos) | G5: clinica@buchinger-wilhelmi.es; +34 952 764 300 | H5: Su congreso de longevidad necesita presencia digital en español; encaje directo con "vive mucho" | I5: 4 | J5: 4 | K5: 2 | L5: =I5+J5+K5 -> 10 | M5: =IF(L5>=10,"Alta",IF(L5>=7,"Media","Baja")) -> Alta | N5: Fuente
A6: 5 | B6: Olympia Quirónsalud – Unidad de Longevidad | C6: Unidad de longevidad hospitalaria | D6: España | E6: Madrid | F6: Unidad de longevidad y lifestyle center de uno de los mayores grupos hospitalarios privados de España | G6: Formulario web olympia.quironsalud.com | H6: Grupo sanitario con línea de medicina de estilo de vida; posible portal educativo de longevidad | I6: 4 | J6: 4 | K6: 1 | L6: =I6+J6+K6 -> 9 | M6: =IF(L6>=10,"Alta",IF(L6>=7,"Media","Baja")) -> Media | N6: Fuente
A7: 6 | B7: Lonvida – Alfredo Carvajal (CEO) / Dr. Yosafat Audiffred | C7: Clínica de longevidad y medicina regenerativa | D7: México | E7: CDMX, Polanco (Goldsmith 38, piso 3); apertura en Los Cabos | F7: Células madre, NAD+, check-ups de precisión; certificación COFEPRIS | G7: contacto@lonvida.com; Tel +52 55 9794 6262; WhatsApp +52 55 7906 4445 | H7: Su propio nombre juega con "longevidad + vida"; en plena expansión, necesitan activos digitales memorables | I7: 5 | J7: 4 | K7: 2 | L7: =I7+J7+K7 -> 11 | M7: =IF(L7>=10,"Alta",IF(L7>=7,"Media","Baja")) -> Alta | N7: Fuente
A8: 7 | B8: Wellness Care – Dra. Vanessa Rivera (Directora) | C8: Clínica de longevidad | D8: Colombia | E8: Medellín, El Poblado (Calle 7 Sur #42-70, Cons. 1013) | F8: Única clínica en LatAm con recambio terapéutico de plasma; 500+ pacientes tratados | G8: administracion@well-ness.care; WhatsApp +57 324 399 9128 | H8: Clínica pionera que capta pacientes internacionales; un dominio fácil de recordar en español potencia su turismo médico | I8: 5 | J8: 3 | K8: 2 | L8: =I8+J8+K8 -> 10 | M8: =IF(L8>=10,"Alta",IF(L8>=7,"Media","Baja")) -> Alta | N8: Fuente
A9: 8 | B9: Dr. William Joaquí ("Dr. Joaqui") | C9: Médico regenerativo / divulgador biohacking | D9: Colombia | E9: Medellín (Edificio Torre Intermédica, Cl. 7 #39-197, Cons. 1717) | F9: Clínica de células madre y péptidos; contenido de biohacking en español con gran alcance | G9: Formulario en drjoaqui.com | H9: Divulgador de biohacking y longevidad; "vive mucho" resume su narrativa de optimización | I9: 4 | J9: 3 | K9: 1 | L9: =I9+J9+K9 -> 8 | M9: =IF(L9>=10,"Alta",IF(L9>=7,"Media","Baja")) -> Media | N9: Fuente
A10: 9 | B10: Longevity Institute | C10: Clínica de células madre y medicina regenerativa | D10: México | E10: México | F10: Se presentan como líderes en México en terapia celular y longevidad | G10: Formulario en longevity-institute.com/es | H10: Su marca es genérica en inglés; un dominio emocional en español les diferenciaría en LatAm | I10: 4 | J10: 3 | K10: 1 | L10: =I10+J10+K10 -> 8 | M10: =IF(L10>=10,"Alta",IF(L10>=7,"Media","Baja")) -> Media | N10: Fuente
A11: 10 | B11: Dr. Julio Effio | C11: Médico cardiólogo pro-aging | D11: Panamá | E11: Ciudad de Panamá | F11: Cardiólogo enfocado en medicina de longevidad; participante del Longevity World Forum | G11: Vía Instagram (perfil público) | H11: Referente de la longevidad en Panamá; dominio útil para consulta y contenidos | I11: 3 | J11: 2 | K11: 1 | L11: =I11+J11+K11 -> 6 | M11: =IF(L11>=10,"Alta",IF(L11>=7,"Media","Baja")) -> Baja | N11: Fuente
A12: 11 | B12: Marcos Vázquez – Fitness Revolucionario | C12: Autor / podcaster de salud | D12: España | E12: Gijón, Asturias | F12: Uno de los blogs y podcasts de salud más importantes en español; autor de "Invicto" y "Salud Salvaje" | G12: fitnessrevolucionario@gmail.com; marcos@fitnessrevolucionario.com | H12: Su mensaje es vitalidad y "salud salvaje"; dominio perfecto para un nuevo proyecto, comunidad o programa | I12: 5 | J12: 5 | K12: 2 | L12: =I12+J12+K12 -> 12 | M12: =IF(L12>=10,"Alta",IF(L12>=7,"Media","Baja")) -> Alta | N12: Fuente
A13: 12 | B13: Dra. Odile Fernández (@misrecetasanticancer) | C13: Médica / autora / emprendedora suplementos | D13: España | E13: España | F13: Superviviente de cáncer; libros bestseller de alimentación anticáncer; línea de suplementos OFM | G13: info@ofm-health.com | H13: Vende libros y suplementos de vida saludable; dominio con gancho emocional para e-commerce y campañas | I13: 4 | J13: 4 | K13: 2 | L13: =I13+J13+K13 -> 10 | M13: =IF(L13>=10,"Alta",IF(L13>=7,"Media","Baja")) -> Alta | N13: Fuente
A14: 13 | B14: Dr. Borja Bandera | C14: Médico divulgador de nutrición | D14: España | E14: Málaga | F14: Autor de varios bestsellers de nutrición; gran audiencia en Instagram y YouTube | G14: No verificado (buscar en su web/IG) | H14: Comunicador masivo de hábitos saludables; encaje natural con el doble sentido del dominio | I14: 4 | J14: 5 | L14: =I14+J14+K14 -> 9 | M14: =IF(L14>=10,"Alta",IF(L14>=7,"Media","Baja")) -> Media | N14: Fuente
A15: 14 | B15: Aitor Sánchez – Mi Dieta Cojea | C15: Dietista-nutricionista / autor | D15: España | E15: España | F15: Referente de la divulgación nutricional en español; varios libros | G15: No verificado (buscar en su blog) | H15: Proyecto educativo sobre alimentación real; posible portal de recursos | I15: 3 | J15: 4 | L15: =I15+J15+K15 -> 7 | M15: =IF(L15>=10,"Alta",IF(L15>=7,"Media","Baja")) -> Media | N15: Fuente
A16: 15 | B16: Victoria Lozada (@nutritionisthenewblack) | C16: Dietista-nutricionista / autora | D16: Venezuela / España | E16: España | F16: ~293K seguidores IG y ~613K en TikTok; autora de 4 libros | G16: Formulario en nutritionisthenewblack.com | H16: Marca personal fuerte en nutrición sin obsesión; dominio para comunidad o academia | I16: 3 | J16: 4 | K16: 1 | L16: =I16+J16+K16 -> 8 | M16: =IF(L16>=10,"Alta",IF(L16>=7,"Media","Baja")) -> Media | N16: Fuente
A17: 16 | B17: Dra. Sari Arponen | C17: Médica PhD / autora / podcaster | D17: España | E17: Madrid | F17: Bestseller "¡Es la microbiota, idiota!"; docente y divulgadora de salud integrativa | G17: Formulario en drasariarponen.com | H17: Salud integrativa y longevidad desde la microbiota; dominio para cursos o comunidad | I17: 3 | J17: 4 | K17: 1 | L17: =I17+J17+K17 -> 8 | M17: =IF(L17>=10,"Alta",IF(L17>=7,"Media","Baja")) -> Media | N17: Fuente
A18: 17 | B18: Dr. Mario Alonso Puig | C18: Cirujano / conferenciante de bienestar | D18: España | E18: Madrid | F18: Referente del desarrollo personal en español; conferencias internacionales (México, LatAm) | G18: Formulario en su web oficial | H18: Su discurso es literalmente "vivir una vida plena": el segundo significado del dominio | I18: 4 | J18: 5 | K18: 1 | L18: =I18+J18+K18 -> 10 | M18: =IF(L18>=10,"Alta",IF(L18>=7,"Media","Baja")) -> Alta | N18: Fuente
A19: 18 | B19: Dra. Marian Rojas Estapé | C19: Psiquiatra / autora | D19: España | E19: Madrid | F19: Autora del bestseller "Cómo hacer que te pasen cosas buenas"; referente de bienestar emocional | G19: No verificado (buscar en su web oficial) | H19: Bienestar emocional = "vivir plenamente"; encaje temático alto | I19: 3 | J19: 5 | L19: =I19+J19+K19 -> 8 | M19: =IF(L19>=10,"Alta",IF(L19>=7,"Media","Baja")) -> Media | N19: Fuente
A20: 19 | B20: Ana Ibáñez | C20: Neurocientífica / divulgadora | D20: España | E20: Madrid, Barcelona y Valencia | F20: Directora de MindStudio; autora y conferenciante de neurociencia aplicada | G20: WhatsApp: Madrid +34 699 697 386; Barcelona +34 648 031 758; Valencia +34 638 099 456 | H20: Neurociencia aplicada al bienestar y el rendimiento vital | I20: 3 | J20: 3 | K20: 2 | L20: =I20+J20+K20 -> 8 | M20: =IF(L20>=10,"Alta",IF(L20>=7,"Media","Baja")) -> Media | N20: Fuente
A21: 20 | B21: Patry Jordán – Gym Virtual | C21: Influencer fitness / empresaria | D21: España / Andorra | E21: Andorra / España | F21: 1,3M seguidores IG; millones de suscriptores en YouTube; Gym Virtual Center | G21: colaboraciones@patryjordan.com; colaboraciones@gymvirtual.com; soporte@gymvirtual.com | H21: Imperio de fitness en español; dominio para app, comunidad o programa de bienestar | I21: 4 | J21: 5 | K21: 2 | L21: =I21+J21+K21 -> 11 | M21: =IF(L21>=10,"Alta",IF(L21>=7,"Media","Baja")) -> Alta | N21: Fuente
A22: 21 | B22: Dr. Bayter (@doctorbayter) | C22: Médico influencer | D22: Colombia | E22: Colombia (gira nacional "Implacable" por 6 ciudades) | F22: 4,9M seguidores en Instagram; autor de libros de alimentación y salud | G22: lina@latinwe.com (management); WhatsApp +57 301 893 3908 | H22: Audiencia masiva en LatAm; lanza productos y giras de salud constantemente | I22: 4 | J22: 5 | K22: 2 | L22: =I22+J22+K22 -> 11 | M22: =IF(L22>=10,"Alta",IF(L22>=7,"Media","Baja")) -> Alta | N22: Fuente
A23: 22 | B23: Dr. Carlos Jaramillo | C23: Médico funcional / autor / empresario | D23: Colombia | E23: Bogotá | F23: 2,5M seguidores IG; bestseller "El milagro metabólico"; CJ Academy; director científico de Savvy | G23: info@drcarlosjaramillo.com; formulario en drcarlosjaramillo.com/contacto | H23: Ecosistema de cursos y suplementos; el dominio sería marca paraguas ideal de bienestar | I23: 5 | J23: 5 | K23: 2 | L23: =I23+J23+K23 -> 12 | M23: =IF(L23>=10,"Alta",IF(L23>=7,"Media","Baja")) -> Alta | N23: Fuente
A24: 23 | B24: Dr. Juan Rivera – Santo Remedio | C24: Médico de TV / emprendedor de suplementos | D24: EE.UU. (mercado hispano) | E24: Miami, Florida | F24: Corresponsal médico jefe de Univision; fundador de Santo Remedio (2020) | G24: support@misantoremedio.com; 1-855-736-3346 | H24: Vende suplementos a hispanos en EE.UU.; "ViveMucho" sería nombre perfecto para línea de productos o campaña | I24: 5 | J24: 5 | K24: 2 | L24: =I24+J24+K24 -> 12 | M24: =IF(L24>=10,"Alta",IF(L24>=7,"Media","Baja")) -> Alta | N24: Fuente
A25: 24 | B25: Se Regalan Dudas – Lety Sahagún y Ashley Frangie | C25: Podcast / ecosistema de bienestar | D25: México | E25: Ciudad de México | F25: Podcast nº1 en español sobre salud mental, amor propio y relaciones; giras por LatAm | G25: Formulario en seregalandudas.com | H25: Ecosistema de herramientas para vivir mejor; dominio para comunidad o plataforma | I25: 3 | J25: 5 | K25: 1 | L25: =I25+J25+K25 -> 9 | M25: =IF(L25>=10,"Alta",IF(L25>=7,"Media","Baja")) -> Media | N25: Fuente
A26: 25 | B26: be levels – Dr. Antonio Hernández y Rocío Périz | C26: Marca de suplementos | D26: España | E26: España | F26: 3.000+ profesionales de la salud la recomiendan; 28 patentes; +20.000 reseñas | G26: Formulario en belevels.com | H26: Su eslogan "A life worth living" es la traducción exacta del doble sentido de ViveMucho | I26: 5 | J26: 4 | K26: 1 | L26: =I26+J26+K26 -> 10 | M26: =IF(L26>=10,"Alta",IF(L26>=7,"Media","Baja")) -> Alta | N26: Fuente
A27: 26 | B27: NDL Pro-Health – Rafa Nadal + Cantabria Labs | C27: Marca de suplementos y nutrición deportiva | D27: España | E27: España | F27: Marca de Rafa Nadal; plan de triplicar ingresos y expansión internacional | G27: Formulario en ndlprohealth.com | H27: En plena expansión al bienestar diario; dominio para campaña en mercado hispano | I27: 4 | J27: 4 | K27: 1 | L27: =I27+J27+K27 -> 9 | M27: =IF(L27>=10,"Alta",IF(L27>=7,"Media","Baja")) -> Media | N27: Fuente
A28: 27 | B28: Yaba (Yaba Ventures S.A.) | C28: Holding de marcas de bienestar | D28: España | E28: Barcelona (Av. Reina Maria Cristina 9, 08004) | F28: Crea y adquiere marcas "para fomentar una vida más larga y plena" | G28: contact@yaba.life | H28: Su misión corporativa es literalmente "vida más larga y plena" = el doble sentido exacto del dominio; y adquieren marcas | I28: 5 | J28: 4 | K28: 2 | L28: =I28+J28+K28 -> 11 | M28: =IF(L28>=10,"Alta",IF(L28>=7,"Media","Baja")) -> Alta | N28: Fuente
A29: 28 | B29: Terraflos | C29: Consumer science / suplementos de longevidad | D29: Argentina / Uruguay | E29: Argentina | F29: Ronda Pre-Serie A de US$3,5M; valorada en US$85M; marcas Vitalis Navitas y NutriCo | G29: Formulario en terraflos.com | H29: Startup de longevidad con capital fresco que lanza marcas; comprador natural de dominios de categoría | I29: 5 | J29: 3 | K29: 1 | L29: =I29+J29+K29 -> 9 | M29: =IF(L29>=10,"Alta",IF(L29>=7,"Media","Baja")) -> Media | N29: Fuente
A30: 29 | B30: Axia Longevity | C30: Startup de suplementos de longevidad | D30: España | E30: España | F30: Diseña suplementos para mejorar la salud celular | G30: No verificado (buscar en su web) | H30: Startup de longevidad que necesita posicionamiento y marca en español | I30: 4 | J30: 2 | L30: =I30+J30+K30 -> 6 | M30: =IF(L30>=10,"Alta",IF(L30>=7,"Media","Baja")) -> Baja | N30: Fuente
A31: 30 | B31: Dr. Joaquín Blázquez | C31: Médico regenerativo / estética funcional | D31: España | E31: Madrid (Calle de Luchana 21, Chamberí) | F31: Clínica propia de medicina regenerativa y estética funcional | G31: Vía Instagram/web (no verificado) | H31: Medicina regenerativa con enfoque en calidad de vida | I31: 3 | J31: 2 | L31: =I31+J31+K31 -> 5 | M31: =IF(L31>=10,"Alta",IF(L31>=7,"Media","Baja")) -> Baja | N31: Fuente
A32: 31 | B32: Clínica Keval+ – Dr. Hernández (fundador y director médico) | C32: Clínica de medicina integrativa antienvejecimiento | D32: España | E32: España | F32: Especializado en nutrición, medicina integrativa y antienvejecimiento; presencia en medios | G32: No verificado (buscar en web de la clínica) | H32: Medicina antienvejecimiento con enfoque en hábitos para sumar años de vida | I32: 3 | J32: 2 | L32: =I32+J32+K32 -> 5 | M32: =IF(L32>=10,"Alta",IF(L32>=7,"Media","Baja")) -> Baja | N32: Fuente
A33: 32 | B33: Savvy Nutrición | C33: Marca de suplementos | D33: México / EE.UU. | E33: México | F33: Marca de suplementos con el Dr. Carlos Jaramillo como director científico | G33: Formulario en youaresavvy.com | H33: Marca en crecimiento con respaldo científico; dominio para expansión de marca | I33: 3 | J33: 3 | K33: 1 | L33: =I33+J33+K33 -> 7 | M33: =IF(L33>=10,"Alta",IF(L33>=7,"Media","Baja")) -> Media | N33: Fuente
A34: 33 | B34: Adrián Gaspar – Espacio Gaspar | C34: Formador en longevidad saludable | D34: Argentina | E34: Argentina | F34: Dirige diplomado en Longevidad Saludable y Calidad de Vida | G34: Vía Instagram (no verificado) | H34: Formación en longevidad; dominio para plataforma educativa | I34: 2 | J34: 2 | L34: =I34+J34+K34 -> 4 | M34: =IF(L34>=10,"Alta",IF(L34>=7,"Media","Baja")) -> Baja | N34: Fuente
A35: 34 | B35: Iván Zhelyazkov (@muymedico) | C35: Médico divulgador | D35: España | E35: España | F35: +200.000 seguidores en Instagram; apuntes de medicina | G35: Vía Instagram (no verificado) | H35: Divulgación médica con audiencia joven | I35: 2 | J35: 3 | L35: =I35+J35+K35 -> 5 | M35: =IF(L35>=10,"Alta",IF(L35>=7,"Media","Baja")) -> Baja | N35: Fuente
A36: 35 | B36: Jonathan Olivera (@soyhumanologo) | C36: Influencer de salud y bienestar | D36: LatAm | E36: LatAm | F36: Listado entre los top influencers hispanos de salud | G36: Vía Instagram (no verificado) | H36: Contenido de bienestar integral | I36: 2 | J36: 3 | L36: =I36+J36+K36 -> 5 | M36: =IF(L36>=10,"Alta",IF(L36>=7,"Media","Baja")) -> Baja | N36: Fuente
A38: Nota: los campos marcados como "No verificado" están pendientes de confirmar en el sitio oficial del prospecto. Ningún email, teléfono ni cifra de este listado ha sido inventado: todo proviene de la fuente enlazada en la columna N.

Sheet Comparables
A1: Dominio | B1: Tipo / significado | C1: Precio (USD) | D1: Fecha | E1: Comprador / contexto | F1: Relevancia para ViveMucho/VivaMucho | G1: Clasificación | H1: Fuente
A2: Viajes.com | B2: Palabra genérica española ("viajes") | C2: 452599 | D2: Feb-2015 | E2: Amado Martín (€400.000); inversor/empresa de viajes | F2: Techo del mercado: genérico de categoría masiva. ViveMucho es una frase brandable de dos palabras, vale una fracción de esto | G2: Techo | H2: www.dnjournal.com
A3: Juegos.com | B3: Palabra genérica española ("juegos") | C3: 1000000 | D3: 2000 (venta original; revendido después) | E3: Empresa europea de juegos online | F3: Techo histórico de los genéricos en español | G3: Techo | H3: dnjournal.com
A4: Vivo.com | B4: Palabra española ("vivo" = primera persona de vivir) | C4: 2100000 | D4: Sep-2016 | E4: Vivo, fabricante chino de smartphones (marca idéntica) | F4: Muestra el valor de la raíz "viv-" cuando hay comprador estratégico con bolsillo profundo | G4: Techo | H4: www.namepros.com
A5: Club.com | B5: Palabra española e inglesa | C5: 10000000 | D5: 2026 | E5: Venta reportada por DNJournal (YTD chart) | F5: Contexto del techo absoluto del mercado premium actual | G5: Contexto | H5: www.dnjournal.com
A6: AI.com | B6: Genérico premium | C6: 70000000 | D6: 2025/2026 | E6: Mayor venta de dominio jamás registrada | F6: Solo contexto de mercado; no comparable directo | G6: Contexto | H6: www.dnjournal.com
A7: CreditCards.com | B7: Keyword comercial inglesa de dos palabras | C7: 2750000 | D7: Jul-2004 | E7: ClickSuccess L.P. (empresa de marketing) | F7: Referencia: keywords comerciales de dos palabras en categorías de alto valor | G7: Contexto | H7: www.dnjournal.com
A8: Longevity.app | B8: Keyword "longevity" en TLD .app | C8: 74988 | D8: Abr-2026 | E8: Venta en Top.domains reportada por DNJournal | F8: Comparable MÁS directo de la temática: la keyword longevidad mueve precios altos; un .com en español de la misma temática vale varias veces un .app | G8: Directa | H8: www.dnjournal.com
A9: Flourish.ai | B9: Keyword de bienestar ("flourish") en .ai | C9: 165000 | D9: 2026 | E9: Venta de Braden Pollock reportada por DNJournal | F9: Keywords de bienestar/vida plena alcanzan seis cifras incluso en TLDs alternativos | G9: Directa | H9: www.dnjournal.com
A10: Evan.com | B10: Nombre propio brandable | C10: 400000 | D10: 2026 | E10: Venta reportada por DNJournal | F10: Referencia de brandables premium en el mercado actual | G10: Contexto | H10: www.dnjournal.com
A11: Enhance.com | B11: Palabra de diccionario inglés | C11: 20000 | D11: Nov-2003 | E11: Subasta Afternic | F11: Piso histórico para diccionarios de una palabra en subasta | G11: Piso | H11: www.dnjournal.com
A13: Nota metodológica: ~90% de las ventas de dominios no se reportan públicamente (Domain Holdings). Estas cifras son ventas públicas verificadas y sirven de anclas: los genéricos de una palabra marcan el techo; las keywords temáticas en TLDs alternativos marcan la referencia directa.

Sheet Valoración
A1: Valoración de ViveMucho.com / VivaMucho.com — anclaje en ventas reales
A3: Ancla | B3: Dominio(s) de referencia | C3: Precio (USD) | D3: Interpretación
A4: Ancla directa temática | B4: Longevity.app / Flourish.ai | C4: =AVERAGE(Comparables!C8,Comparables!C9) -> 119994 | D4: La temática exacta (longevidad/vida plena) mueve 75K–165K USD incluso en TLDs alternativos; el .com en español es el activo superior de la misma temática
A5: Techo genéricos españoles | B5: Viajes.com / Vivo.com | C5: =AVERAGE(Comparables!C2,Comparables!C4) -> 1276299.5 | D5: Genéricos de UNA palabra marcan el techo (0,45–2,1M USD); una frase brandable de dos palabras vale típicamente un 5–15% de esa referencia
A6: Descuento dos palabras (hipótesis editable) | B6: — | C6: 0.1 | D6: Hipótesis central: ViveMucho ≈ 10% del valor de un genérico de una palabra de categoría similar
A8: Escenario | B8: Supuesto | C8: Precio por dominio (USD) | D8: Pack 2 dominios (USD) | E8: Tipo de comprador típico
A9: Conservador (piso) | B9: Venta a emprendedor individual o proyecto nuevo, sin competencia de compradores | C9: =C6*Comparables!C2 -> 45259.9 | D9: =C9*1.8 -> 81467.82 | E9: Divulgadores, coaches, proyectos nuevos
A10: Central (recomendado) | B10: Ancla directa temática × prima .com sobre .app/.ai (1,5×) | C10: =AVERAGE(Comparables!C8,Comparables!C9)*1.5 -> 179991 | D10: =C10*1.8 -> 323983.8 | E10: Marcas de suplementos, autores con negocio, clínicas medianas
A11: Optimista (techo realista) | B11: Máxima venta directa × prima .com (1,5×) | C11: =MAX(Comparables!C8,Comparables!C9)*1.5 -> 247500 | D11: =C11*1.8 -> 445500 | E11: Clínicas premium, holdings de marcas, marcas de TV
A12: Estratégico (jackpot) | B12: 15% de la referencia Vivo.com: solo si aparece un comprador cuya marca ES 'Vive Mucho' | C12: =Comparables!C4*0.15 -> 315000 | D12: =C12*1.8 -> 567000 | E12: Empresa que lance la marca 'Vive Mucho'
A14: Nota: el pack de ambos dominios se calcula a 1,8× el precio individual (el segundo dominio funciona como defensivo/redirect y no duplica valor). Todas las cifras se derivan por fórmulas de la hoja Comparables, no de estimaciones cerradas.
A16: Recomendación de precio
A17: Precio de salida recomendado (listado) | B17: =ROUND(C11,-3) -> 248000 | C17: Se lista en el techo realista para dejar margen de negociación
A18: Rango aceptable de cierre | B18: =TEXT(ROUND(C9,-3),"$#,##0")&" – "&TEXT(ROUND(C10,-3),"$#,##0") -> $45,000 – $180,000 | C18: Piso–central según tipo de comprador
A19: No aceptar menos de | B19: =ROUND(C9*0.7,-3) -> 32000 | C19: Por debajo de esto se regala el activo
A21: Las tasaciones automáticas (GoDaddy/Estibot) suelen infravalorar los brandables hispanos porque se entrenan con ventas en inglés; por eso el anclaje usa ventas reales de la misma temática. El escenario estratégico NO es precio de salida: solo aplica si aparece un comprador con marca idéntica.
A23: Estrategia de salida
A24: 1. Prioridad | B24: Contactar primero a los 15 prospectos de prioridad 'Alta' de la hoja Prospectos: los compradores estratégicos (usuario final) pagan 5–20× más que los inversores de dominios
A25: 2. Listado pasivo | B25: Listar además en Sedo/Afternic/Atom con precio BIN en el techo realista para captar demanda pasiva
A26: 3. Mensaje | B26: El pitch vende el DOBLE sentido: longevidad ('vivir muchos años') + vida plena ('vivir mucho, intensamente')
A27: 4. Negociación | B27: Ofrecer el pack de 2 dominios: el segundo se percibe como regalo defensivo y sube el ticket medio
A28: 5. Defensa | B28: Renovar ambos dominios varios años antes de contactar (señal de no-urgencia)
